{
 "Colorful": {
  "name": "Colorful",
  "bl_idname": "ShaderNodeTree",
  "interface": [
   {
    "default_value": [
     0.0,
     0.0,
     0.0,
     0.0
    ],
    "identifier": "Socket_0",
    "in_out": "OUTPUT",
    "index": 0,
    "item_type": "SOCKET",
    "name": "Color",
    "position": 0,
    "socket_type": "NodeSocketColor",
    "HN_parent_idx": -1
   },
   {
    "default_value": 0.5,
    "identifier": "Socket_3",
    "in_out": "INPUT",
    "index": 1,
    "item_type": "SOCKET",
    "max_value": 1.0,
    "min_value": 0.0,
    "name": "Mix Color",
    "position": 1,
    "socket_type": "NodeSocketFloat",
    "subtype": "FACTOR",
    "HN_parent_idx": -1
   },
   {
    "default_value": [
     0.5,
     0.5,
     0.5,
     1.0
    ],
    "identifier": "Socket_4",
    "in_out": "INPUT",
    "index": 2,
    "item_type": "SOCKET",
    "name": "Color",
    "position": 2,
    "socket_type": "NodeSocketColor",
    "HN_parent_idx": -1
   }
  ],
  "nodes": {
   "Group Output": {
    "bl_idname": "NodeGroupOutput",
    "location": [
     477.9993591308594,
     0.0
    ],
    "name": "Group Output"
   },
   "Group Input": {
    "bl_idname": "NodeGroupInput",
    "location": [
     -304.10760498046875,
     -213.5658416748047
    ],
    "name": "Group Input"
   },
   "ColorRamp": {
    "bl_idname": "ShaderNodeValToRGB",
    "color_ramp": {
     "color_mode": "HSL",
     "elements": [
      {
       "color": [
        1.0,
        0.98447585105896,
        0.8918750882148743,
        1.0
       ],
       "position": 0.0,
       "HN_idx": 0
      },
      {
       "color": [
        1.0,
        0.7239852547645569,
        0.41929933428764343,
        1.0
       ],
       "position": 1.0,
       "HN_idx": 1
      }
     ],
     "hue_interpolation": "FAR"
    },
    "location": [
     -117.31199645996094,
     33.890953063964844
    ],
    "name": "ColorRamp",
    "outputs": [
     {
      "default_value": [
       0.0,
       0.0,
       0.0,
       0.0
      ],
      "HN_idx": 0
     }
    ]
   },
   "Layer Weight": {
    "bl_idname": "ShaderNodeLayerWeight",
    "location": [
     -270.7274169921875,
     -61.862403869628906
    ],
    "name": "Layer Weight"
   },
   "Mix": {
    "bl_idname": "ShaderNodeMix",
    "data_type": "RGBA",
    "inputs": [
     {
      "enabled": false,
      "HN_idx": 2
     },
     {
      "enabled": false,
      "HN_idx": 3
     },
     {
      "enabled": true,
      "HN_idx": 6
     },
     {
      "enabled": true,
      "HN_idx": 7
     }
    ],
    "location": [
     258.2916259765625,
     -2.0631866455078125
    ],
    "name": "Mix",
    "outputs": [
     {
      "enabled": false,
      "HN_idx": 0
     },
     {
      "enabled": true,
      "HN_idx": 2
     }
    ]
   }
  },
  "links": [
   {
    "HN_from_node_name": "Layer Weight",
    "HN_to_node_name": "ColorRamp",
    "HN_from_socket_idx": 1,
    "HN_to_socket_idx": 0
   },
   {
    "HN_from_node_name": "Mix",
    "HN_to_node_name": "Group Output",
    "HN_from_socket_idx": 2,
    "HN_to_socket_idx": 0
   },
   {
    "HN_from_node_name": "ColorRamp",
    "HN_to_node_name": "Mix",
    "HN_from_socket_idx": 0,
    "HN_to_socket_idx": 6
   },
   {
    "HN_from_node_name": "Group Input",
    "HN_to_node_name": "Mix",
    "HN_from_socket_idx": 0,
    "HN_to_socket_idx": 0
   },
   {
    "HN_from_node_name": "Group Input",
    "HN_to_node_name": "Mix",
    "HN_from_socket_idx": 1,
    "HN_to_socket_idx": 7
   }
  ]
 },
 "HN_edit_tree": {
  "name": "Shader Nodetree",
  "bl_idname": "ShaderNodeTree",
  "interface": [],
  "nodes": {
   "Group": {
    "bl_idname": "ShaderNodeGroup",
    "location": [
     -557.3787841796875,
     284.4824523925781
    ],
    "name": "Group",
    "HN_nt_name": "Colorful"
   }
  },
  "links": []
 },
 "HN_preset_data": {
  "preset_name": "Colorful Ray",
  "pack_name": "Default Set",
  "tree_type": "ShaderNodeTree",
  "node_center": [
   -557.3787841796875,
   284.4824523925781
  ],
  "version": [
   0,
   2,
   0
  ]
 }
}