{
 "HN_edit_tree": {
  "name": "Outline_Geo_1.0",
  "bl_idname": "GeometryNodeTree",
  "interface": [
   {
    "identifier": "Output_1",
    "in_out": "OUTPUT",
    "index": 0,
    "item_type": "SOCKET",
    "name": "Geonetry",
    "position": 0,
    "socket_type": "NodeSocketGeometry",
    "HN_parent_idx": -1
   },
   {
    "identifier": "Input_0",
    "in_out": "INPUT",
    "index": 1,
    "item_type": "SOCKET",
    "name": "Geonetry",
    "position": 1,
    "socket_type": "NodeSocketGeometry",
    "HN_parent_idx": -1
   },
   {
    "default_value": 1.0,
    "identifier": "Input_2",
    "in_out": "INPUT",
    "index": 2,
    "item_type": "SOCKET",
    "max_value": 1024.0,
    "min_value": 0.0,
    "name": "Width",
    "position": 2,
    "socket_type": "NodeSocketFloat",
    "HN_parent_idx": -1
   },
   {
    "default_value": 1.0,
    "identifier": "Input_6",
    "in_out": "INPUT",
    "index": 3,
    "item_type": "SOCKET",
    "max_value": 1024.0,
    "min_value": 0.0,
    "name": "Z Offset",
    "position": 3,
    "socket_type": "NodeSocketFloat",
    "HN_parent_idx": -1
   },
   {
    "default_value": true,
    "force_non_field": true,
    "identifier": "Socket_4",
    "in_out": "INPUT",
    "index": 4,
    "item_type": "SOCKET",
    "name": "Auto Thickness",
    "position": 4,
    "socket_type": "NodeSocketBool",
    "HN_parent_idx": -1
   },
   {
    "identifier": "Input_4",
    "in_out": "INPUT",
    "index": 5,
    "item_type": "SOCKET",
    "name": "Camera",
    "position": 5,
    "socket_type": "NodeSocketObject",
    "HN_parent_idx": -1
   },
   {
    "default_value": "Col",
    "identifier": "Socket_5",
    "in_out": "INPUT",
    "index": 6,
    "item_type": "SOCKET",
    "name": "Outline Vertex Color",
    "position": 6,
    "socket_type": "NodeSocketString",
    "HN_parent_idx": -1
   },
   {
    "default_attribute_name": "edge",
    "identifier": "Input_3",
    "in_out": "INPUT",
    "index": 7,
    "item_type": "SOCKET",
    "name": "Outline Vertex Group",
    "position": 7,
    "socket_type": "NodeSocketBool",
    "HN_parent_idx": -1
   },
   {
    "default_attribute_name": "tex1",
    "default_value": true,
    "hide_value": true,
    "identifier": "Input_7",
    "in_out": "INPUT",
    "index": 8,
    "item_type": "SOCKET",
    "name": "Tex1 Vertex",
    "position": 8,
    "socket_type": "NodeSocketBool",
    "HN_parent_idx": -1
   },
   {
    "default_attribute_name": "tex2",
    "default_value": true,
    "hide_value": true,
    "identifier": "Socket_0",
    "in_out": "INPUT",
    "index": 9,
    "item_type": "SOCKET",
    "name": "Tex2 Vertex",
    "position": 9,
    "socket_type": "NodeSocketBool",
    "HN_parent_idx": -1
   },
   {
    "default_attribute_name": "tex3",
    "default_value": true,
    "hide_value": true,
    "identifier": "Socket_2",
    "in_out": "INPUT",
    "index": 10,
    "item_type": "SOCKET",
    "name": "Tex3 Vertex",
    "position": 10,
    "socket_type": "NodeSocketBool",
    "HN_parent_idx": -1
   },
   {
    "default_attribute_name": "tex4",
    "default_value": true,
    "hide_value": true,
    "identifier": "Socket_3",
    "in_out": "INPUT",
    "index": 11,
    "item_type": "SOCKET",
    "name": "Tex4 Vertex",
    "position": 11,
    "socket_type": "NodeSocketBool",
    "HN_parent_idx": -1
   }
  ],
  "nodes": {
   "Frame.002": {
    "bl_idname": "NodeFrame",
    "label": "View Offset",
    "location": [
     54.62921142578125,
     -162.71099853515625
    ],
    "name": "Frame.002"
   },
   "Frame": {
    "bl_idname": "NodeFrame",
    "label": "Detect tex selection: 0 or 1 or overflow",
    "location": [
     -1192.8348388671875,
     -498.05517578125
    ],
    "name": "Frame"
   },
   "Frame.001": {
    "bl_idname": "NodeFrame",
    "label": "Select tex 1-4 or 0",
    "location": [
     -1161.5755615234375,
     -316.77740478515625
    ],
    "name": "Frame.001"
   },
   "Frame.004": {
    "bl_idname": "NodeFrame",
    "label": "Default 0, tex 1-4, overflow warning 5",
    "location": [
     68.4488525390625,
     -26.9102783203125
    ],
    "name": "Frame.004"
   },
   "Frame.003": {
    "bl_idname": "NodeFrame",
    "label": "Outline Width",
    "location": [
     -172.3897705078125,
     124.67715454101562
    ],
    "name": "Frame.003"
   },
   "Math": {
    "bl_idname": "ShaderNodeMath",
    "inputs": [
     {
      "default_value": -0.9999991655349731,
      "display_shape": "CIRCLE",
      "HN_idx": 0
     },
     {
      "default_value": -0.0010000000474974513,
      "display_shape": "CIRCLE",
      "HN_idx": 1
     },
     {
      "display_shape": "CIRCLE",
      "HN_idx": 2
     }
    ],
    "location": [
     -444.5665588378906,
     -413.6243896484375
    ],
    "name": "Math",
    "operation": "MULTIPLY",
    "outputs": [
     {
      "display_shape": "CIRCLE",
      "HN_idx": 0
     }
    ],
    "HN_ref2_node_attr": "parent",
    "HN_ref2_node_name": "Frame.002"
   },
   "Vector Rotate": {
    "bl_idname": "ShaderNodeVectorRotate",
    "inputs": [
     {
      "display_shape": "CIRCLE",
      "HN_idx": 0
     },
     {
      "display_shape": "CIRCLE",
      "HN_idx": 1
     },
     {
      "display_shape": "CIRCLE",
      "enabled": false,
      "HN_idx": 2
     },
     {
      "display_shape": "CIRCLE",
      "enabled": false,
      "HN_idx": 3
     },
     {
      "display_shape": "CIRCLE",
      "enabled": true,
      "HN_idx": 4
     }
    ],
    "location": [
     -83.36348724365234,
     -412.2687683105469
    ],
    "name": "Vector Rotate",
    "outputs": [
     {
      "display_shape": "CIRCLE",
      "HN_idx": 0
     }
    ],
    "HN_ref2_node_attr": "parent",
    "HN_ref2_node_name": "Frame.002",
    "rotation_type": "EULER_XYZ"
   },
   "Combine XYZ": {
    "bl_idname": "ShaderNodeCombineXYZ",
    "inputs": [
     {
      "display_shape": "CIRCLE",
      "HN_idx": 0
     },
     {
      "display_shape": "CIRCLE",
      "HN_idx": 1
     },
     {
      "default_value": -0.0010000020265579224,
      "display_shape": "CIRCLE",
      "HN_idx": 2
     }
    ],
    "location": [
     -273.6846618652344,
     -442.2290954589844
    ],
    "name": "Combine XYZ",
    "outputs": [
     {
      "display_shape": "CIRCLE",
      "HN_idx": 0
     }
    ],
    "HN_ref2_node_attr": "parent",
    "HN_ref2_node_name": "Frame.002"
   },
   "\u7269\u4f53\u4fe1\u606f.001": {
    "bl_idname": "GeometryNodeObjectInfo",
    "location": [
     -436.3216552734375,
     -580.4889526367188
    ],
    "name": "\u7269\u4f53\u4fe1\u606f.001",
    "HN_ref2_node_attr": "parent",
    "HN_ref2_node_name": "Frame.002",
    "transform_space": "RELATIVE"
   },
   "\u7ec4\u8f93\u5165.003": {
    "bl_idname": "NodeGroupInput",
    "location": [
     -658.7977294921875,
     -488.3221130371094
    ],
    "name": "\u7ec4\u8f93\u5165.003",
    "outputs": [
     {
      "default_value": 0.0,
      "HN_idx": 1
     },
     {
      "default_value": -0.9999991655349731,
      "HN_idx": 2
     },
     {
      "default_value": false,
      "HN_idx": 3
     },
     {
      "default_value": false,
      "HN_idx": 10
     }
    ],
    "HN_ref2_node_attr": "parent",
    "HN_ref2_node_name": "Frame.002"
   },
   "\u8bbe\u7f6e\u6750\u8d28.004": {
    "bl_idname": "GeometryNodeSetMaterial",
    "location": [
     2009.1536865234375,
     -178.6606903076172
    ],
    "name": "\u8bbe\u7f6e\u6750\u8d28.004",
    "width": 169.2660369873047
   },
   "\u51e0\u4f55\u5230\u5b9e\u4f8b": {
    "bl_idname": "GeometryNodeGeometryToInstance",
    "location": [
     2211.56982421875,
     -173.92315673828125
    ],
    "name": "\u51e0\u4f55\u5230\u5b9e\u4f8b"
   },
   "\u8bbe\u7f6e\u7740\u8272\u5e73\u6ed1": {
    "bl_idname": "GeometryNodeSetShadeSmooth",
    "location": [
     137.0866241455078,
     -26.369077682495117
    ],
    "name": "\u8bbe\u7f6e\u7740\u8272\u5e73\u6ed1"
   },
   "\u6309\u8ddd\u79bb\u5408\u5e76": {
    "bl_idname": "GeometryNodeMergeByDistance",
    "inputs": [
     {
      "default_value": 9.999999747378752e-05,
      "HN_idx": 2
     }
    ],
    "location": [
     345.75927734375,
     -22.07106590270996
    ],
    "name": "\u6309\u8ddd\u79bb\u5408\u5e76"
   },
   "Transform Geometry": {
    "bl_idname": "GeometryNodeTransform",
    "location": [
     1074.6435546875,
     -182.178466796875
    ],
    "name": "Transform Geometry"
   },
   "\u7ffb\u8f6c\u9762": {
    "bl_idname": "GeometryNodeFlipFaces",
    "location": [
     1297.3492431640625,
     -174.287841796875
    ],
    "name": "\u7ffb\u8f6c\u9762"
   },
   "\u8bbe\u7f6e\u4f4d\u7f6e": {
    "bl_idname": "GeometryNodeSetPosition",
    "inputs": [
     {
      "display_shape": "DIAMOND",
      "HN_idx": 3
     }
    ],
    "location": [
     858.8721923828125,
     -110.79035186767578
    ],
    "name": "\u8bbe\u7f6e\u4f4d\u7f6e"
   },
   "\u7ec4\u8f93\u5165.001": {
    "bl_idname": "NodeGroupInput",
    "location": [
     -51.50494384765625,
     54.66563034057617
    ],
    "name": "\u7ec4\u8f93\u5165.001",
    "outputs": [
     {
      "default_value": 0.0,
      "HN_idx": 1
     },
     {
      "default_value": -0.9999991655349731,
      "HN_idx": 2
     },
     {
      "default_value": false,
      "HN_idx": 3
     },
     {
      "default_value": false,
      "HN_idx": 10
     }
    ]
   },
   "\u7ec4\u8f93\u51fa": {
    "bl_idname": "NodeGroupOutput",
    "location": [
     2574.52197265625,
     -103.6201171875
    ],
    "name": "\u7ec4\u8f93\u51fa"
   },
   "Store Named Attribute": {
    "bl_idname": "GeometryNodeStoreNamedAttribute",
    "inputs": [
     {
      "default_value": "OutlineTexOrder",
      "HN_idx": 2
     },
     {
      "display_shape": "DIAMOND",
      "HN_idx": 3
     }
    ],
    "location": [
     1761.04736328125,
     -176.0345916748047
    ],
    "name": "Store Named Attribute",
    "width": 220.72152709960938
   },
   "\u5408\u5e76\u51e0\u4f55": {
    "bl_idname": "GeometryNodeJoinGeometry",
    "location": [
     2403.1806640625,
     -105.20783233642578
    ],
    "name": "\u5408\u5e76\u51e0\u4f55"
   },
   "\u7ec4\u8f93\u5165.004": {
    "bl_idname": "NodeGroupInput",
    "location": [
     1376.8934326171875,
     -1008.562744140625
    ],
    "name": "\u7ec4\u8f93\u5165.004",
    "outputs": [
     {
      "default_value": 0.0,
      "HN_idx": 1
     },
     {
      "default_value": -0.9999991655349731,
      "HN_idx": 2
     },
     {
      "default_value": false,
      "HN_idx": 3
     },
     {
      "default_value": false,
      "HN_idx": 10
     }
    ],
    "HN_ref2_node_attr": "parent",
    "HN_ref2_node_name": "Frame"
   },
   "Math.007": {
    "bl_idname": "ShaderNodeMath",
    "inputs": [
     {
      "display_shape": "DIAMOND",
      "HN_idx": 0
     },
     {
      "display_shape": "DIAMOND",
      "HN_idx": 1
     }
    ],
    "location": [
     1633.31689453125,
     -966.326904296875
    ],
    "name": "Math.007",
    "outputs": [
     {
      "display_shape": "DIAMOND",
      "HN_idx": 0
     }
    ],
    "HN_ref2_node_attr": "parent",
    "HN_ref2_node_name": "Frame"
   },
   "Math.008": {
    "bl_idname": "ShaderNodeMath",
    "inputs": [
     {
      "display_shape": "DIAMOND",
      "HN_idx": 0
     },
     {
      "display_shape": "DIAMOND",
      "HN_idx": 1
     }
    ],
    "location": [
     1631.8310546875,
     -1116.9593505859375
    ],
    "name": "Math.008",
    "outputs": [
     {
      "display_shape": "DIAMOND",
      "HN_idx": 0
     }
    ],
    "HN_ref2_node_attr": "parent",
    "HN_ref2_node_name": "Frame"
   },
   "Math.009": {
    "bl_idname": "ShaderNodeMath",
    "inputs": [
     {
      "display_shape": "DIAMOND",
      "HN_idx": 0
     },
     {
      "display_shape": "DIAMOND",
      "HN_idx": 1
     }
    ],
    "location": [
     1802.4385986328125,
     -1002.341796875
    ],
    "name": "Math.009",
    "outputs": [
     {
      "display_shape": "DIAMOND",
      "HN_idx": 0
     }
    ],
    "HN_ref2_node_attr": "parent",
    "HN_ref2_node_name": "Frame"
   },
   "Math.011": {
    "bl_idname": "ShaderNodeMath",
    "inputs": [
     {
      "display_shape": "DIAMOND",
      "HN_idx": 0
     },
     {
      "default_value": 1.100000023841858,
      "label": "Threshold",
      "HN_idx": 1
     },
     {
      "default_value": 0.10000000149011612,
      "HN_idx": 2
     }
    ],
    "location": [
     1985.111572265625,
     -1143.513427734375
    ],
    "name": "Math.011",
    "operation": "GREATER_THAN",
    "outputs": [
     {
      "display_shape": "DIAMOND",
      "HN_idx": 0
     }
    ],
    "HN_ref2_node_attr": "parent",
    "HN_ref2_node_name": "Frame"
   },
   "Math.010": {
    "bl_idname": "ShaderNodeMath",
    "inputs": [
     {
      "display_shape": "DIAMOND",
      "HN_idx": 0
     },
     {
      "default_value": 1.0,
      "HN_idx": 1
     },
     {
      "default_value": 0.10000000149011612,
      "enabled": true,
      "label": "Epsilon",
      "HN_idx": 2
     }
    ],
    "location": [
     1985.238037109375,
     -975.6939697265625
    ],
    "name": "Math.010",
    "operation": "COMPARE",
    "outputs": [
     {
      "display_shape": "DIAMOND",
      "HN_idx": 0
     }
    ],
    "HN_ref2_node_attr": "parent",
    "HN_ref2_node_name": "Frame"
   },
   "Math.001": {
    "bl_idname": "ShaderNodeMath",
    "inputs": [
     {
      "default_value": 1.0,
      "HN_idx": 0
     },
     {
      "display_shape": "DIAMOND",
      "HN_idx": 1
     }
    ],
    "location": [
     1623.6317138671875,
     -461.9916687011719
    ],
    "name": "Math.001",
    "operation": "MULTIPLY",
    "outputs": [
     {
      "display_shape": "DIAMOND",
      "HN_idx": 0
     }
    ],
    "HN_ref2_node_attr": "parent",
    "HN_ref2_node_name": "Frame.001"
   },
   "Math.002": {
    "bl_idname": "ShaderNodeMath",
    "inputs": [
     {
      "default_value": 2.0,
      "HN_idx": 0
     },
     {
      "display_shape": "DIAMOND",
      "HN_idx": 1
     }
    ],
    "location": [
     1623.73583984375,
     -613.72216796875
    ],
    "name": "Math.002",
    "operation": "MULTIPLY",
    "outputs": [
     {
      "display_shape": "DIAMOND",
      "HN_idx": 0
     }
    ],
    "HN_ref2_node_attr": "parent",
    "HN_ref2_node_name": "Frame.001"
   },
   "Math.003": {
    "bl_idname": "ShaderNodeMath",
    "inputs": [
     {
      "default_value": 3.0,
      "HN_idx": 0
     },
     {
      "display_shape": "DIAMOND",
      "HN_idx": 1
     }
    ],
    "location": [
     1621.64453125,
     -763.7102661132812
    ],
    "name": "Math.003",
    "operation": "MULTIPLY",
    "outputs": [
     {
      "display_shape": "DIAMOND",
      "HN_idx": 0
     }
    ],
    "HN_ref2_node_attr": "parent",
    "HN_ref2_node_name": "Frame.001"
   },
   "\u7ec4\u8f93\u5165.005": {
    "bl_idname": "NodeGroupInput",
    "location": [
     1381.6339111328125,
     -587.3607788085938
    ],
    "name": "\u7ec4\u8f93\u5165.005",
    "outputs": [
     {
      "default_value": 0.0,
      "HN_idx": 1
     },
     {
      "default_value": -0.9999991655349731,
      "HN_idx": 2
     },
     {
      "default_value": false,
      "HN_idx": 3
     },
     {
      "default_value": false,
      "HN_idx": 10
     }
    ],
    "HN_ref2_node_attr": "parent",
    "HN_ref2_node_name": "Frame.001"
   },
   "Math.006": {
    "bl_idname": "ShaderNodeMath",
    "inputs": [
     {
      "default_value": 1.0,
      "display_shape": "DIAMOND",
      "HN_idx": 0
     },
     {
      "display_shape": "DIAMOND",
      "HN_idx": 1
     }
    ],
    "location": [
     1942.4027099609375,
     -614.7544555664062
    ],
    "name": "Math.006",
    "outputs": [
     {
      "display_shape": "DIAMOND",
      "HN_idx": 0
     }
    ],
    "HN_ref2_node_attr": "parent",
    "HN_ref2_node_name": "Frame.001"
   },
   "Math.005": {
    "bl_idname": "ShaderNodeMath",
    "inputs": [
     {
      "default_value": 1.0,
      "display_shape": "DIAMOND",
      "HN_idx": 0
     },
     {
      "display_shape": "DIAMOND",
      "HN_idx": 1
     }
    ],
    "location": [
     1786.016357421875,
     -585.8690795898438
    ],
    "name": "Math.005",
    "outputs": [
     {
      "display_shape": "DIAMOND",
      "HN_idx": 0
     }
    ],
    "HN_ref2_node_attr": "parent",
    "HN_ref2_node_name": "Frame.001"
   },
   "Math.012": {
    "bl_idname": "ShaderNodeMath",
    "inputs": [
     {
      "default_value": 3.0,
      "display_shape": "DIAMOND",
      "HN_idx": 0
     },
     {
      "default_value": 4.0,
      "HN_idx": 1
     }
    ],
    "location": [
     1625.168212890625,
     -921.5131225585938
    ],
    "name": "Math.012",
    "operation": "MULTIPLY",
    "outputs": [
     {
      "display_shape": "DIAMOND",
      "HN_idx": 0
     }
    ],
    "HN_ref2_node_attr": "parent",
    "HN_ref2_node_name": "Frame.001"
   },
   "Math.013": {
    "bl_idname": "ShaderNodeMath",
    "inputs": [
     {
      "default_value": 1.0,
      "display_shape": "DIAMOND",
      "HN_idx": 0
     },
     {
      "display_shape": "DIAMOND",
      "HN_idx": 1
     }
    ],
    "location": [
     1786.831298828125,
     -739.1760864257812
    ],
    "name": "Math.013",
    "outputs": [
     {
      "display_shape": "DIAMOND",
      "HN_idx": 0
     }
    ],
    "HN_ref2_node_attr": "parent",
    "HN_ref2_node_name": "Frame.001"
   },
   "Mix": {
    "bl_idname": "ShaderNodeMix",
    "inputs": [
     {
      "display_shape": "DIAMOND",
      "HN_idx": 0
     },
     {
      "display_shape": "DIAMOND",
      "HN_idx": 2
     },
     {
      "default_value": 5.0,
      "HN_idx": 3
     }
    ],
    "location": [
     1314.67138671875,
     -1113.4510498046875
    ],
    "name": "Mix",
    "outputs": [
     {
      "display_shape": "DIAMOND",
      "HN_idx": 0
     },
     {
      "display_shape": "DIAMOND",
      "HN_idx": 1
     },
     {
      "default_value": [
       0.0,
       0.0,
       0.0,
       0.0
      ],
      "display_shape": "DIAMOND",
      "HN_idx": 2
     },
     {
      "display_shape": "DIAMOND",
      "HN_idx": 3
     }
    ],
    "HN_ref2_node_attr": "parent",
    "HN_ref2_node_name": "Frame.004"
   },
   "Math.004": {
    "bl_idname": "ShaderNodeMath",
    "inputs": [
     {
      "default_value": 1.0,
      "display_shape": "DIAMOND",
      "HN_idx": 0
     },
     {
      "display_shape": "DIAMOND",
      "HN_idx": 1
     }
    ],
    "location": [
     1031.0296630859375,
     -1129.6552734375
    ],
    "name": "Math.004",
    "operation": "MULTIPLY",
    "outputs": [
     {
      "display_shape": "DIAMOND",
      "HN_idx": 0
     }
    ],
    "HN_ref2_node_attr": "parent",
    "HN_ref2_node_name": "Frame.004"
   },
   "\u7ec4\u8f93\u5165.002": {
    "bl_idname": "NodeGroupInput",
    "location": [
     1653.3548583984375,
     118.41644287109375
    ],
    "name": "\u7ec4\u8f93\u5165.002",
    "outputs": [
     {
      "default_value": 0.0,
      "HN_idx": 1
     },
     {
      "default_value": -0.9999991655349731,
      "HN_idx": 2
     },
     {
      "default_value": false,
      "HN_idx": 3
     },
     {
      "default_value": false,
      "HN_idx": 10
     }
    ]
   },
   "\u7269\u4f53\u4fe1\u606f": {
    "bl_idname": "GeometryNodeObjectInfo",
    "location": [
     -1403.9942626953125,
     -348.688232421875
    ],
    "name": "\u7269\u4f53\u4fe1\u606f",
    "HN_ref2_node_attr": "parent",
    "HN_ref2_node_name": "Frame.003",
    "transform_space": "RELATIVE"
   },
   "\u4f4d\u7f6e": {
    "bl_idname": "GeometryNodeInputPosition",
    "location": [
     -1405.6046142578125,
     -283.8204650878906
    ],
    "name": "\u4f4d\u7f6e",
    "HN_ref2_node_attr": "parent",
    "HN_ref2_node_name": "Frame.003"
   },
   "\u77e2\u91cf\u8fd0\u7b97.001": {
    "bl_idname": "ShaderNodeVectorMath",
    "inputs": [
     {
      "display_shape": "DIAMOND",
      "HN_idx": 0
     }
    ],
    "location": [
     -1231.8907470703125,
     -298.0718994140625
    ],
    "name": "\u77e2\u91cf\u8fd0\u7b97.001",
    "operation": "DISTANCE",
    "outputs": [
     {
      "display_shape": "DIAMOND",
      "enabled": false,
      "HN_idx": 0
     },
     {
      "display_shape": "DIAMOND",
      "enabled": true,
      "HN_idx": 1
     }
    ],
    "HN_ref2_node_attr": "parent",
    "HN_ref2_node_name": "Frame.003"
   },
   "\u8fd0\u7b97.003": {
    "bl_idname": "ShaderNodeMath",
    "inputs": [
     {
      "display_shape": "DIAMOND",
      "HN_idx": 0
     },
     {
      "default_value": 0.4000000059604645,
      "enabled": false,
      "HN_idx": 1
     }
    ],
    "location": [
     -1073.871826171875,
     -290.7484436035156
    ],
    "name": "\u8fd0\u7b97.003",
    "operation": "ARCTANGENT",
    "outputs": [
     {
      "display_shape": "DIAMOND",
      "HN_idx": 0
     }
    ],
    "HN_ref2_node_attr": "parent",
    "HN_ref2_node_name": "Frame.003"
   },
   "\u8fd0\u7b97.004": {
    "bl_idname": "ShaderNodeMath",
    "inputs": [
     {
      "display_shape": "DIAMOND",
      "HN_idx": 0
     },
     {
      "default_value": 0.2499999850988388,
      "HN_idx": 1
     }
    ],
    "location": [
     -696.2649536132812,
     -292.21337890625
    ],
    "name": "\u8fd0\u7b97.004",
    "outputs": [
     {
      "display_shape": "DIAMOND",
      "HN_idx": 0
     }
    ],
    "HN_ref2_node_attr": "parent",
    "HN_ref2_node_name": "Frame.003"
   },
   "\u8fd0\u7b97.002": {
    "bl_idname": "ShaderNodeMath",
    "inputs": [
     {
      "display_shape": "DIAMOND",
      "HN_idx": 0
     },
     {
      "display_shape": "DIAMOND",
      "HN_idx": 1
     }
    ],
    "location": [
     -448.29888916015625,
     -156.67210388183594
    ],
    "name": "\u8fd0\u7b97.002",
    "operation": "MULTIPLY",
    "outputs": [
     {
      "display_shape": "DIAMOND",
      "HN_idx": 0
     }
    ],
    "HN_ref2_node_attr": "parent",
    "HN_ref2_node_name": "Frame.003"
   },
   "\u8fd0\u7b97": {
    "bl_idname": "ShaderNodeMath",
    "inputs": [
     {
      "display_shape": "DIAMOND",
      "HN_idx": 0
     },
     {
      "default_value": 0.0010000000474974513,
      "HN_idx": 1
     }
    ],
    "location": [
     -274.4820251464844,
     -156.11021423339844
    ],
    "name": "\u8fd0\u7b97",
    "operation": "MULTIPLY",
    "outputs": [
     {
      "display_shape": "DIAMOND",
      "HN_idx": 0
     }
    ],
    "HN_ref2_node_attr": "parent",
    "HN_ref2_node_name": "Frame.003"
   },
   "\u77e2\u91cf\u8fd0\u7b97": {
    "bl_idname": "ShaderNodeVectorMath",
    "inputs": [
     {
      "display_shape": "DIAMOND",
      "HN_idx": 0
     },
     {
      "display_shape": "DIAMOND",
      "HN_idx": 1
     }
    ],
    "location": [
     -89.03966522216797,
     -177.51670837402344
    ],
    "name": "\u77e2\u91cf\u8fd0\u7b97",
    "operation": "MULTIPLY",
    "outputs": [
     {
      "display_shape": "DIAMOND",
      "HN_idx": 0
     },
     {
      "display_shape": "DIAMOND",
      "HN_idx": 1
     }
    ],
    "HN_ref2_node_attr": "parent",
    "HN_ref2_node_name": "Frame.003"
   },
   "\u6cd5\u5411": {
    "bl_idname": "GeometryNodeInputNormal",
    "location": [
     -285.6494140625,
     -323.8905944824219
    ],
    "name": "\u6cd5\u5411",
    "HN_ref2_node_attr": "parent",
    "HN_ref2_node_name": "Frame.003"
   },
   "\u8fd0\u7b97.001": {
    "bl_idname": "ShaderNodeMath",
    "inputs": [
     {
      "display_shape": "DIAMOND",
      "HN_idx": 0
     }
    ],
    "location": [
     -909.8425903320312,
     -116.58076477050781
    ],
    "name": "\u8fd0\u7b97.001",
    "operation": "MULTIPLY",
    "outputs": [
     {
      "display_shape": "DIAMOND",
      "HN_idx": 0
     }
    ],
    "HN_ref2_node_attr": "parent",
    "HN_ref2_node_name": "Frame.003"
   },
   "Named Attribute": {
    "bl_idname": "GeometryNodeInputNamedAttribute",
    "data_type": "FLOAT_COLOR",
    "inputs": [
     {
      "default_value": "Col",
      "HN_idx": 0
     }
    ],
    "location": [
     -1407.1888427734375,
     -144.87548828125
    ],
    "name": "Named Attribute",
    "outputs": [
     {
      "default_value": [
       0.0,
       0.0,
       0.0,
       0.0
      ],
      "HN_idx": 0
     }
    ],
    "HN_ref2_node_attr": "parent",
    "HN_ref2_node_name": "Frame.003"
   },
   "\u7ec4\u8f93\u5165": {
    "bl_idname": "NodeGroupInput",
    "location": [
     -1604.7374267578125,
     -251.90731811523438
    ],
    "name": "\u7ec4\u8f93\u5165",
    "outputs": [
     {
      "default_value": 0.0,
      "HN_idx": 1
     },
     {
      "default_value": -0.9999991655349731,
      "HN_idx": 2
     },
     {
      "default_value": false,
      "HN_idx": 3
     },
     {
      "default_value": false,
      "HN_idx": 10
     }
    ],
    "HN_ref2_node_attr": "parent",
    "HN_ref2_node_name": "Frame.003"
   },
   "Separate Color": {
    "bl_idname": "FunctionNodeSeparateColor",
    "inputs": [
     {
      "display_shape": "DIAMOND",
      "HN_idx": 0
     }
    ],
    "location": [
     -1228.4254150390625,
     -115.7396011352539
    ],
    "name": "Separate Color",
    "outputs": [
     {
      "display_shape": "DIAMOND",
      "HN_idx": 0
     },
     {
      "display_shape": "DIAMOND",
      "HN_idx": 1
     },
     {
      "display_shape": "DIAMOND",
      "HN_idx": 2
     },
     {
      "display_shape": "DIAMOND",
      "HN_idx": 3
     }
    ],
    "HN_ref2_node_attr": "parent",
    "HN_ref2_node_name": "Frame.003"
   },
   "\u8fd0\u7b97.005": {
    "bl_idname": "ShaderNodeMath",
    "inputs": [
     {
      "display_shape": "DIAMOND",
      "HN_idx": 0
     },
     {
      "display_shape": "DIAMOND",
      "HN_idx": 1
     }
    ],
    "location": [
     -1065.9530029296875,
     -114.20602416992188
    ],
    "name": "\u8fd0\u7b97.005",
    "outputs": [
     {
      "display_shape": "DIAMOND",
      "HN_idx": 0
     }
    ],
    "HN_ref2_node_attr": "parent",
    "HN_ref2_node_name": "Frame.003",
    "use_clamp": true
   },
   "Mix.001": {
    "bl_idname": "ShaderNodeMix",
    "inputs": [
     {
      "default_value": 1.0,
      "HN_idx": 2
     },
     {
      "display_shape": "DIAMOND",
      "HN_idx": 3
     }
    ],
    "location": [
     -908.8927001953125,
     -283.08868408203125
    ],
    "name": "Mix.001",
    "outputs": [
     {
      "display_shape": "DIAMOND",
      "HN_idx": 0
     },
     {
      "display_shape": "DIAMOND",
      "HN_idx": 1
     },
     {
      "display_shape": "DIAMOND",
      "HN_idx": 2
     },
     {
      "display_shape": "DIAMOND",
      "HN_idx": 3
     }
    ],
    "HN_ref2_node_attr": "parent",
    "HN_ref2_node_name": "Frame.003"
   }
  },
  "links": [
   {
    "HN_from_node_name": "Transform Geometry",
    "HN_to_node_name": "\u7ffb\u8f6c\u9762",
    "HN_from_socket_idx": 0,
    "HN_to_socket_idx": 0
   },
   {
    "HN_from_node_name": "\u6cd5\u5411",
    "HN_to_node_name": "\u77e2\u91cf\u8fd0\u7b97",
    "HN_from_socket_idx": 0,
    "HN_to_socket_idx": 1
   },
   {
    "HN_from_node_name": "\u77e2\u91cf\u8fd0\u7b97",
    "HN_to_node_name": "\u8bbe\u7f6e\u4f4d\u7f6e",
    "HN_from_socket_idx": 0,
    "HN_to_socket_idx": 3
   },
   {
    "HN_from_node_name": "\u8fd0\u7b97.002",
    "HN_to_node_name": "\u8fd0\u7b97",
    "HN_from_socket_idx": 0,
    "HN_to_socket_idx": 0
   },
   {
    "HN_from_node_name": "\u8fd0\u7b97.005",
    "HN_to_node_name": "\u8fd0\u7b97.001",
    "HN_from_socket_idx": 0,
    "HN_to_socket_idx": 0
   },
   {
    "HN_from_node_name": "\u4f4d\u7f6e",
    "HN_to_node_name": "\u77e2\u91cf\u8fd0\u7b97.001",
    "HN_from_socket_idx": 0,
    "HN_to_socket_idx": 0
   },
   {
    "HN_from_node_name": "\u7269\u4f53\u4fe1\u606f",
    "HN_to_node_name": "\u77e2\u91cf\u8fd0\u7b97.001",
    "HN_from_socket_idx": 1,
    "HN_to_socket_idx": 1
   },
   {
    "HN_from_node_name": "\u8fd0\u7b97.001",
    "HN_to_node_name": "\u8fd0\u7b97.002",
    "HN_from_socket_idx": 0,
    "HN_to_socket_idx": 0
   },
   {
    "HN_from_node_name": "\u8fd0\u7b97.004",
    "HN_to_node_name": "\u8fd0\u7b97.002",
    "HN_from_socket_idx": 0,
    "HN_to_socket_idx": 1
   },
   {
    "HN_from_node_name": "\u77e2\u91cf\u8fd0\u7b97.001",
    "HN_to_node_name": "\u8fd0\u7b97.003",
    "HN_from_socket_idx": 1,
    "HN_to_socket_idx": 0
   },
   {
    "HN_from_node_name": "Mix.001",
    "HN_to_node_name": "\u8fd0\u7b97.004",
    "HN_from_socket_idx": 0,
    "HN_to_socket_idx": 0
   },
   {
    "HN_from_node_name": "\u7ec4\u8f93\u5165.002",
    "HN_to_node_name": "\u5408\u5e76\u51e0\u4f55",
    "HN_from_socket_idx": 0,
    "HN_to_socket_idx": 0
   },
   {
    "HN_from_node_name": "\u8bbe\u7f6e\u7740\u8272\u5e73\u6ed1",
    "HN_to_node_name": "\u6309\u8ddd\u79bb\u5408\u5e76",
    "HN_from_socket_idx": 0,
    "HN_to_socket_idx": 0
   },
   {
    "HN_from_node_name": "\u7ec4\u8f93\u5165",
    "HN_to_node_name": "\u7269\u4f53\u4fe1\u606f",
    "HN_from_socket_idx": 4,
    "HN_to_socket_idx": 0
   },
   {
    "HN_from_node_name": "Combine XYZ",
    "HN_to_node_name": "Vector Rotate",
    "HN_from_socket_idx": 0,
    "HN_to_socket_idx": 0
   },
   {
    "HN_from_node_name": "\u8bbe\u7f6e\u4f4d\u7f6e",
    "HN_to_node_name": "Transform Geometry",
    "HN_from_socket_idx": 0,
    "HN_to_socket_idx": 0
   },
   {
    "HN_from_node_name": "Vector Rotate",
    "HN_to_node_name": "Transform Geometry",
    "HN_from_socket_idx": 0,
    "HN_to_socket_idx": 1
   },
   {
    "HN_from_node_name": "Math",
    "HN_to_node_name": "Combine XYZ",
    "HN_from_socket_idx": 0,
    "HN_to_socket_idx": 2
   },
   {
    "HN_from_node_name": "\u7ec4\u8f93\u5165.001",
    "HN_to_node_name": "\u8bbe\u7f6e\u7740\u8272\u5e73\u6ed1",
    "HN_from_socket_idx": 0,
    "HN_to_socket_idx": 0
   },
   {
    "HN_from_node_name": "\u6309\u8ddd\u79bb\u5408\u5e76",
    "HN_to_node_name": "\u8bbe\u7f6e\u4f4d\u7f6e",
    "HN_from_socket_idx": 0,
    "HN_to_socket_idx": 0
   },
   {
    "HN_from_node_name": "\u8fd0\u7b97",
    "HN_to_node_name": "\u77e2\u91cf\u8fd0\u7b97",
    "HN_from_socket_idx": 0,
    "HN_to_socket_idx": 0
   },
   {
    "HN_from_node_name": "\u8bbe\u7f6e\u6750\u8d28.004",
    "HN_to_node_name": "\u51e0\u4f55\u5230\u5b9e\u4f8b",
    "HN_from_socket_idx": 0,
    "HN_to_socket_idx": 0
   },
   {
    "HN_from_node_name": "\u51e0\u4f55\u5230\u5b9e\u4f8b",
    "HN_to_node_name": "\u5408\u5e76\u51e0\u4f55",
    "HN_from_socket_idx": 0,
    "HN_to_socket_idx": 0
   },
   {
    "HN_from_node_name": "\u7ec4\u8f93\u5165.005",
    "HN_to_node_name": "Math.003",
    "HN_from_socket_idx": 9,
    "HN_to_socket_idx": 1
   },
   {
    "HN_from_node_name": "\u7ec4\u8f93\u5165.005",
    "HN_to_node_name": "Math.002",
    "HN_from_socket_idx": 8,
    "HN_to_socket_idx": 1
   },
   {
    "HN_from_node_name": "\u7ec4\u8f93\u5165.005",
    "HN_to_node_name": "Math.001",
    "HN_from_socket_idx": 7,
    "HN_to_socket_idx": 1
   },
   {
    "HN_from_node_name": "Math.001",
    "HN_to_node_name": "Math.005",
    "HN_from_socket_idx": 0,
    "HN_to_socket_idx": 0
   },
   {
    "HN_from_node_name": "Math.002",
    "HN_to_node_name": "Math.005",
    "HN_from_socket_idx": 0,
    "HN_to_socket_idx": 1
   },
   {
    "HN_from_node_name": "Math.005",
    "HN_to_node_name": "Math.006",
    "HN_from_socket_idx": 0,
    "HN_to_socket_idx": 0
   },
   {
    "HN_from_node_name": "Math.006",
    "HN_to_node_name": "Math.004",
    "HN_from_socket_idx": 0,
    "HN_to_socket_idx": 0
   },
   {
    "HN_from_node_name": "Mix",
    "HN_to_node_name": "Store Named Attribute",
    "HN_from_socket_idx": 0,
    "HN_to_socket_idx": 3
   },
   {
    "HN_from_node_name": "Store Named Attribute",
    "HN_to_node_name": "\u8bbe\u7f6e\u6750\u8d28.004",
    "HN_from_socket_idx": 0,
    "HN_to_socket_idx": 0
   },
   {
    "HN_from_node_name": "\u7269\u4f53\u4fe1\u606f.001",
    "HN_to_node_name": "Vector Rotate",
    "HN_from_socket_idx": 2,
    "HN_to_socket_idx": 4
   },
   {
    "HN_from_node_name": "\u7ec4\u8f93\u5165.003",
    "HN_to_node_name": "Math",
    "HN_from_socket_idx": 2,
    "HN_to_socket_idx": 0
   },
   {
    "HN_from_node_name": "\u7ec4\u8f93\u5165.003",
    "HN_to_node_name": "\u7269\u4f53\u4fe1\u606f.001",
    "HN_from_socket_idx": 4,
    "HN_to_socket_idx": 0
   },
   {
    "HN_from_node_name": "\u7ffb\u8f6c\u9762",
    "HN_to_node_name": "Store Named Attribute",
    "HN_from_socket_idx": 0,
    "HN_to_socket_idx": 0
   },
   {
    "HN_from_node_name": "\u5408\u5e76\u51e0\u4f55",
    "HN_to_node_name": "\u7ec4\u8f93\u51fa",
    "HN_from_socket_idx": 0,
    "HN_to_socket_idx": 0
   },
   {
    "HN_from_node_name": "\u7ec4\u8f93\u5165.004",
    "HN_to_node_name": "Math.007",
    "HN_from_socket_idx": 7,
    "HN_to_socket_idx": 0
   },
   {
    "HN_from_node_name": "\u7ec4\u8f93\u5165.004",
    "HN_to_node_name": "Math.007",
    "HN_from_socket_idx": 8,
    "HN_to_socket_idx": 1
   },
   {
    "HN_from_node_name": "\u7ec4\u8f93\u5165.004",
    "HN_to_node_name": "Math.008",
    "HN_from_socket_idx": 9,
    "HN_to_socket_idx": 0
   },
   {
    "HN_from_node_name": "\u7ec4\u8f93\u5165.004",
    "HN_to_node_name": "Math.008",
    "HN_from_socket_idx": 10,
    "HN_to_socket_idx": 1
   },
   {
    "HN_from_node_name": "Math.007",
    "HN_to_node_name": "Math.009",
    "HN_from_socket_idx": 0,
    "HN_to_socket_idx": 0
   },
   {
    "HN_from_node_name": "Math.008",
    "HN_to_node_name": "Math.009",
    "HN_from_socket_idx": 0,
    "HN_to_socket_idx": 1
   },
   {
    "HN_from_node_name": "Math.009",
    "HN_to_node_name": "Math.010",
    "HN_from_socket_idx": 0,
    "HN_to_socket_idx": 0
   },
   {
    "HN_from_node_name": "Math.009",
    "HN_to_node_name": "Math.011",
    "HN_from_socket_idx": 0,
    "HN_to_socket_idx": 0
   },
   {
    "HN_from_node_name": "Math.010",
    "HN_to_node_name": "Math.004",
    "HN_from_socket_idx": 0,
    "HN_to_socket_idx": 1
   },
   {
    "HN_from_node_name": "Math.004",
    "HN_to_node_name": "Mix",
    "HN_from_socket_idx": 0,
    "HN_to_socket_idx": 2
   },
   {
    "HN_from_node_name": "Math.011",
    "HN_to_node_name": "Mix",
    "HN_from_socket_idx": 0,
    "HN_to_socket_idx": 0
   },
   {
    "HN_from_node_name": "\u7ec4\u8f93\u5165.005",
    "HN_to_node_name": "Math.012",
    "HN_from_socket_idx": 10,
    "HN_to_socket_idx": 0
   },
   {
    "HN_from_node_name": "Math.012",
    "HN_to_node_name": "Math.013",
    "HN_from_socket_idx": 0,
    "HN_to_socket_idx": 1
   },
   {
    "HN_from_node_name": "Math.003",
    "HN_to_node_name": "Math.013",
    "HN_from_socket_idx": 0,
    "HN_to_socket_idx": 0
   },
   {
    "HN_from_node_name": "Math.013",
    "HN_to_node_name": "Math.006",
    "HN_from_socket_idx": 0,
    "HN_to_socket_idx": 1
   },
   {
    "HN_from_node_name": "Named Attribute",
    "HN_to_node_name": "Separate Color",
    "HN_from_socket_idx": 0,
    "HN_to_socket_idx": 0
   },
   {
    "HN_from_node_name": "\u7ec4\u8f93\u5165",
    "HN_to_node_name": "Named Attribute",
    "HN_from_socket_idx": 5,
    "HN_to_socket_idx": 0
   },
   {
    "HN_from_node_name": "Separate Color",
    "HN_to_node_name": "\u8fd0\u7b97.005",
    "HN_from_socket_idx": 3,
    "HN_to_socket_idx": 0
   },
   {
    "HN_from_node_name": "\u7ec4\u8f93\u5165",
    "HN_to_node_name": "\u8fd0\u7b97.005",
    "HN_from_socket_idx": 6,
    "HN_to_socket_idx": 1
   },
   {
    "HN_from_node_name": "\u8fd0\u7b97.003",
    "HN_to_node_name": "Mix.001",
    "HN_from_socket_idx": 0,
    "HN_to_socket_idx": 3
   },
   {
    "HN_from_node_name": "\u7ec4\u8f93\u5165",
    "HN_to_node_name": "Mix.001",
    "HN_from_socket_idx": 3,
    "HN_to_socket_idx": 0
   }
  ]
 },
 "HN_preset_data": {
  "preset_name": "Outline Geo 1.0",
  "pack_name": "Default Set",
  "tree_type": "GeometryNodeTree",
  "node_center": [
   551.9949804941813,
   -427.4109687805176
  ],
  "version": [
   0,
   2,
   0
  ]
 }
}